hikerapi/__init__.py
hikerapi/__version__.py
hikerapi/api.py
hikerapi/asyncapi.py
hikerapi/base.py
hikerapi/extractors.py
hikerapi/helpers.py
hikerapi-1.7.4.dist-info/licenses/LICENSE
hikerapi-1.7.4.dist-info/METADATA
hikerapi-1.7.4.dist-info/WHEEL
hikerapi-1.7.4.dist-info/top_level.txt
hikerapi-1.7.4.dist-info/RECORD
